Metadata-Version: 1.1
Name: ladyredhood-chats
Version: 0.1.1
Summary: A small script to extract timestamps from youtube chats
Home-page: https://github.com/aurghya-0/ladyredhood-chat
Author: Aurghyadip Kundu
Author-email: director@webedutech.org
License: MIT
Keywords: youtube youtube-chat youtube-timestamp
Platform: UNKNOWN
Classifier: Development Status :: 4 - Beta
Classifier: Intended Audience :: Developers
Classifier: Topic :: Internet
Classifier: License :: OSI Approved :: MIT License
Classifier: Programming Language :: Python
